fds/__init__.py
fds/sdk/__init__.py
fds/sdk/AssetCashFlowProjections/__init__.py
fds/sdk/AssetCashFlowProjections/api_client.py
fds/sdk/AssetCashFlowProjections/configuration.py
fds/sdk/AssetCashFlowProjections/exceptions.py
fds/sdk/AssetCashFlowProjections/model_utils.py
fds/sdk/AssetCashFlowProjections/rest.py
fds/sdk/AssetCashFlowProjections/api/__init__.py
fds/sdk/AssetCashFlowProjections/api/batch_api.py
fds/sdk/AssetCashFlowProjections/api/documents_api.py
fds/sdk/AssetCashFlowProjections/api/scenarios_api.py
fds/sdk/AssetCashFlowProjections/apis/__init__.py
fds/sdk/AssetCashFlowProjections/model/__init__.py
fds/sdk/AssetCashFlowProjections/model/batch_job_response.py
fds/sdk/AssetCashFlowProjections/model/batch_job_response_root.py
fds/sdk/AssetCashFlowProjections/model/client_error_response.py
fds/sdk/AssetCashFlowProjections/model/client_scenarios_upload.py
fds/sdk/AssetCashFlowProjections/model/client_scenarios_upload_parameters.py
fds/sdk/AssetCashFlowProjections/model/client_upload_response.py
fds/sdk/AssetCashFlowProjections/model/client_upload_response_parameters.py
fds/sdk/AssetCashFlowProjections/model/create_batch_job.py
fds/sdk/AssetCashFlowProjections/model/create_batch_job_root.py
fds/sdk/AssetCashFlowProjections/model/create_new_document.py
fds/sdk/AssetCashFlowProjections/model/create_new_document_root.py
fds/sdk/AssetCashFlowProjections/model/document_response.py
fds/sdk/AssetCashFlowProjections/model/document_response_root.py
fds/sdk/AssetCashFlowProjections/model/error_source.py
fds/sdk/AssetCashFlowProjections/model/errors.py
fds/sdk/AssetCashFlowProjections/model/update_new_document.py
fds/sdk/AssetCashFlowProjections/model/update_new_document_root.py
fds/sdk/AssetCashFlowProjections/model/upload_status_response.py
fds/sdk/AssetCashFlowProjections/model/upload_status_response_parameters.py
fds/sdk/AssetCashFlowProjections/models/__init__.py
fds_sdk_assetcashflowprojections-0.11.0.dist-info/licenses/LICENSE
fds_sdk_assetcashflowprojections-0.11.0.dist-info/METADATA
fds_sdk_assetcashflowprojections-0.11.0.dist-info/WHEEL
fds_sdk_assetcashflowprojections-0.11.0.dist-info/top_level.txt
fds_sdk_assetcashflowprojections-0.11.0.dist-info/RECORD
